{
	"type": "minecraft:chest",
	"pools": [
		{
			"name": "main",
			"rolls": {
				"type": "minecraft:uniform",
				"min": 1.0,
				"max": 2.0
			},
			"bonus_rolls": 0.0,
			"entries": [
				{
					"type": "minecraft:item",
					"functions": [
						{
							"function": "minecraft:enchant_with_levels",
							"levels": {
								"type": "minecraft:uniform",
								"min": 8.0,
								"max": 18.0
							},
							"treasure": false
						}
					],
					"name": "minecraft:book"
				},
				{
					"type": "minecraft:item",
					"functions": [
						{
							"function": "minecraft:set_count",
							"count": {
								"type": "minecraft:uniform",
								"min": 1.0,
								"max": 2.0
							},
							"add": false
						}
					],
					"name": "minecraft:book"
				},
				{
					"type": "minecraft:item",
					"functions": [
						{
							"function": "minecraft:set_count",
							"count": {
								"type": "minecraft:uniform",
								"min": 1.0,
								"max": 4.0
							},
							"add": false
						}
					],
					"name": "minecraft:paper"
				},
				{
					"type": "minecraft:item",
					"functions": [
						{
							"function": "minecraft:set_count",
							"count": {
								"type": "minecraft:uniform",
								"min": 1.0,
								"max": 3.0
							},
							"add": false
						}
					],
					"name": "minecraft:purple_dye"
				}
			]
		},
		{
			"name": "pool1",
			"rolls": 1.0,
			"bonus_rolls": 0.0,
			"entries": [
				{
					"type": "minecraft:item",
					"functions": [
						{
							"function": "minecraft:enchant_with_levels",
							"levels": {
								"type": "minecraft:uniform",
								"min": 10.0,
								"max": 18.0
							},
							"treasure": false
						}
					],
					"name": "minecraft:iron_sword"
				},
				{
					"type": "minecraft:item",
					"functions": [
						{
							"function": "minecraft:enchant_with_levels",
							"levels": {
								"type": "minecraft:uniform",
								"min": 8.0,
								"max": 20.0
							},
							"treasure": false
						}
					],
					"name": "minecraft:stone_sword"
				}
			]
		},
		{
			"name": "pool2",
			"rolls": {
				"type": "minecraft:uniform",
				"min": 0.0,
				"max": 2.0
			},
			"bonus_rolls": 0.0,
			"entries": [
				{
					"type": "minecraft:item",
					"weight": 2,
					"functions": [
						{
							"function": "minecraft:enchant_with_levels",
							"levels": 12.0,
							"treasure": false
						}
					],
					"name": "minecraft:iron_boots"
				},
				{
					"type": "minecraft:item",
					"weight": 2,
					"functions": [
						{
							"function": "minecraft:enchant_with_levels",
							"levels": 12.0,
							"treasure": false
						}
					],
					"name": "minecraft:iron_leggings"
				},
				{
					"type": "minecraft:item",
					"weight": 2,
					"functions": [
						{
							"function": "minecraft:enchant_with_levels",
							"levels": 12.0,
							"treasure": false
						}
					],
					"name": "minecraft:iron_helmet"
				},
				{
					"type": "minecraft:item",
					"weight": 2,
					"functions": [
						{
							"function": "minecraft:enchant_with_levels",
							"levels": 12.0,
							"treasure": false
						}
					],
					"name": "minecraft:iron_chestplate"
				}
			]
		},
		{
			"name": "pool3",
			"rolls": {
				"type": "minecraft:uniform",
				"min": 1.0,
				"max": 2.0
			},
			"bonus_rolls": 0.0,
			"entries": [
				{
					"type": "minecraft:item",
					"functions": [
						{
							"function": "minecraft:enchant_with_levels",
							"levels": {
								"type": "minecraft:uniform",
								"min": 10.0,
								"max": 12.0
							},
							"treasure": false
						}
					],
					"name": "minecraft:golden_boots"
				},
				{
					"type": "minecraft:item",
					"functions": [
						{
							"function": "minecraft:enchant_with_levels",
							"levels": {
								"type": "minecraft:uniform",
								"min": 10.0,
								"max": 12.0
							},
							"treasure": false
						}
					],
					"name": "minecraft:golden_leggings"
				},
				{
					"type": "minecraft:item",
					"functions": [
						{
							"function": "minecraft:enchant_with_levels",
							"levels": {
								"type": "minecraft:uniform",
								"min": 10.0,
								"max": 12.0
							},
							"treasure": false
						}
					],
					"name": "minecraft:leather_chestplate"
				},
				{
					"type": "minecraft:item",
					"functions": [
						{
							"function": "minecraft:enchant_with_levels",
							"levels": {
								"type": "minecraft:uniform",
								"min": 10.0,
								"max": 12.0
							},
							"treasure": false
						}
					],
					"name": "minecraft:leather_helmet"
				}
			]
		},
		{
			"name": "pool4",
			"rolls": {
				"type": "minecraft:uniform",
				"min": 1.0,
				"max": 16.0
			},
			"bonus_rolls": 0.0,
			"entries": [
				{
					"type": "minecraft:item",
					"name": "minecraft:slime_ball"
				},
				{
					"type": "minecraft:item",
					"functions": [
						{
							"function": "minecraft:set_count",
							"count": {
								"type": "minecraft:uniform",
								"min": 1.0,
								"max": 3.0
							},
							"add": false
						}
					],
					"name": "minecraft:spruce_planks"
				},
				{
					"type": "minecraft:item",
					"functions": [
						{
							"function": "minecraft:set_count",
							"count": {
								"type": "minecraft:uniform",
								"min": 1.0,
								"max": 4.0
							},
							"add": false
						}
					],
					"name": "minecraft:stick"
				},
				{
					"type": "minecraft:item",
					"functions": [
						{
							"function": "minecraft:set_count",
							"count": {
								"type": "minecraft:uniform",
								"min": 1.0,
								"max": 8.0
							},
							"add": false
						}
					],
					"name": "minecraft:white_wool"
				}
			]
		},
		{
			"name": "pool5",
			"rolls": 1.0,
			"bonus_rolls": 0.0,
			"entries": [
				{
					"type": "minecraft:loot_table",
					"name": "minecraft:chests/pillager_outpost"
				}
			]
		}
	]
}